PyUColor/__init__.py
PyUColor/color.py
PyUColor-0.22.dist-info/METADATA
PyUColor-0.22.dist-info/WHEEL
PyUColor-0.22.dist-info/top_level.txt
PyUColor-0.22.dist-info/RECORD
