Metadata-Version: 2.1
Name: PyUColor
Version: 0.22
Summary: A simple library for printing colored text in the terminal.
Home-page: https://github.com/urielmalka/Print-Color-C
Author: Uriel Malka
Author-email: urielmlka1@gmail.com
Classifier: Programming Language :: Python :: 3
Classifier: License :: OSI Approved :: MIT License
Classifier: Operating System :: OS Independent
Requires-Python: >=3.6
